{
  "configurations": [
    {
      "browse": {
        "databaseFilename": "",
        "limitSymbolsToIncludedHeaders": true
      },
      "includePath": [
        "/opt/ros/foxy/include/**",
        "/usr/include/**",
        "${workspaceFolder}/**",
        "/home/robot/workspace/git_ws/install/action_msg_srv/include/**"
      ],
      "name": "Linux",
      "compilerPath": "/usr/bin/g++",
      "cStandard": "c99",
      "cppStandard": "c++14",
      "intelliSenseMode": "linux-gcc-x64"
    }
  ],
  "version": 4
}
